Workbook

Sheet Assumptions
A1: IFRS 16 租赁计量假设（黄色=输入；绿色=公式；金额：元）
A3: 租赁开始日 | B3: 46388
A4: 每期付款（月末） | B4: 100000
A5: 期数（月） | B5: 24
A6: 年有效折现率 | B6: 0.06
A7: 月折现率 =(1+年率)^(1/12)-1 | B7: =(1+B6)^(1/12)-1
A8: 初始租赁负债（期末付款年金现值） | B8: =B4*(1-(1+B7)^(-B5))/B7
A9: 初始使用权资产 ROU（=初始负债） | B9: =B8
A10: ROU 月折旧（直线） | B10: =B9/B5
A11: 增值税/初始直接成本/预付款/激励/复原义务 | B11: 0
A14: 口径：支付在期末；无增值税、初始直接成本、预付款、激励或复原义务；ROU 按 24 个月直线折旧；显示保留到元，公式保留全精度。

Sheet Schedule
A1: 24 个月租赁负债摊销与 ROU 折旧（元；全部为公式）
A3: Month | B3: Period End Date | C3: Opening Liability | D3: Interest | E3: Payment | F3: Principal | G3: Closing Liability | H3: ROU Depreciation | I3: ROU Carrying Amount | J3: Year
A4: 1 | B4: =EOMONTH(Assumptions!$B$3,0) | C4: =Assumptions!$B$8 | D4: =C4*Assumptions!$B$7 | E4: =Assumptions!$B$4 | F4: =E4-D4 | G4: =C4-F4 | H4: =Assumptions!$B$10 | I4: =Assumptions!$B$9-SUM($H$4:H4) | J4: =YEAR(B4)
A5: 2 | B5: =EOMONTH(Assumptions!$B$3,1) | C5: =G4 | D5: =C5*Assumptions!$B$7 | E5: =Assumptions!$B$4 | F5: =E5-D5 | G5: =C5-F5 | H5: =Assumptions!$B$10 | I5: =Assumptions!$B$9-SUM($H$4:H5) | J5: =YEAR(B5)
A6: 3 | B6: =EOMONTH(Assumptions!$B$3,2) | C6: =G5 | D6: =C6*Assumptions!$B$7 | E6: =Assumptions!$B$4 | F6: =E6-D6 | G6: =C6-F6 | H6: =Assumptions!$B$10 | I6: =Assumptions!$B$9-SUM($H$4:H6) | J6: =YEAR(B6)
A7: 4 | B7: =EOMONTH(Assumptions!$B$3,3) | C7: =G6 | D7: =C7*Assumptions!$B$7 | E7: =Assumptions!$B$4 | F7: =E7-D7 | G7: =C7-F7 | H7: =Assumptions!$B$10 | I7: =Assumptions!$B$9-SUM($H$4:H7) | J7: =YEAR(B7)
A8: 5 | B8: =EOMONTH(Assumptions!$B$3,4) | C8: =G7 | D8: =C8*Assumptions!$B$7 | E8: =Assumptions!$B$4 | F8: =E8-D8 | G8: =C8-F8 | H8: =Assumptions!$B$10 | I8: =Assumptions!$B$9-SUM($H$4:H8) | J8: =YEAR(B8)
A9: 6 | B9: =EOMONTH(Assumptions!$B$3,5) | C9: =G8 | D9: =C9*Assumptions!$B$7 | E9: =Assumptions!$B$4 | F9: =E9-D9 | G9: =C9-F9 | H9: =Assumptions!$B$10 | I9: =Assumptions!$B$9-SUM($H$4:H9) | J9: =YEAR(B9)
A10: 7 | B10: =EOMONTH(Assumptions!$B$3,6) | C10: =G9 | D10: =C10*Assumptions!$B$7 | E10: =Assumptions!$B$4 | F10: =E10-D10 | G10: =C10-F10 | H10: =Assumptions!$B$10 | I10: =Assumptions!$B$9-SUM($H$4:H10) | J10: =YEAR(B10)
A11: 8 | B11: =EOMONTH(Assumptions!$B$3,7) | C11: =G10 | D11: =C11*Assumptions!$B$7 | E11: =Assumptions!$B$4 | F11: =E11-D11 | G11: =C11-F11 | H11: =Assumptions!$B$10 | I11: =Assumptions!$B$9-SUM($H$4:H11) | J11: =YEAR(B11)
A12: 9 | B12: =EOMONTH(Assumptions!$B$3,8) | C12: =G11 | D12: =C12*Assumptions!$B$7 | E12: =Assumptions!$B$4 | F12: =E12-D12 | G12: =C12-F12 | H12: =Assumptions!$B$10 | I12: =Assumptions!$B$9-SUM($H$4:H12) | J12: =YEAR(B12)
A13: 10 | B13: =EOMONTH(Assumptions!$B$3,9) | C13: =G12 | D13: =C13*Assumptions!$B$7 | E13: =Assumptions!$B$4 | F13: =E13-D13 | G13: =C13-F13 | H13: =Assumptions!$B$10 | I13: =Assumptions!$B$9-SUM($H$4:H13) | J13: =YEAR(B13)
A14: 11 | B14: =EOMONTH(Assumptions!$B$3,10) | C14: =G13 | D14: =C14*Assumptions!$B$7 | E14: =Assumptions!$B$4 | F14: =E14-D14 | G14: =C14-F14 | H14: =Assumptions!$B$10 | I14: =Assumptions!$B$9-SUM($H$4:H14) | J14: =YEAR(B14)
A15: 12 | B15: =EOMONTH(Assumptions!$B$3,11) | C15: =G14 | D15: =C15*Assumptions!$B$7 | E15: =Assumptions!$B$4 | F15: =E15-D15 | G15: =C15-F15 | H15: =Assumptions!$B$10 | I15: =Assumptions!$B$9-SUM($H$4:H15) | J15: =YEAR(B15)
A16: 13 | B16: =EOMONTH(Assumptions!$B$3,12) | C16: =G15 | D16: =C16*Assumptions!$B$7 | E16: =Assumptions!$B$4 | F16: =E16-D16 | G16: =C16-F16 | H16: =Assumptions!$B$10 | I16: =Assumptions!$B$9-SUM($H$4:H16) | J16: =YEAR(B16)
A17: 14 | B17: =EOMONTH(Assumptions!$B$3,13) | C17: =G16 | D17: =C17*Assumptions!$B$7 | E17: =Assumptions!$B$4 | F17: =E17-D17 | G17: =C17-F17 | H17: =Assumptions!$B$10 | I17: =Assumptions!$B$9-SUM($H$4:H17) | J17: =YEAR(B17)
A18: 15 | B18: =EOMONTH(Assumptions!$B$3,14) | C18: =G17 | D18: =C18*Assumptions!$B$7 | E18: =Assumptions!$B$4 | F18: =E18-D18 | G18: =C18-F18 | H18: =Assumptions!$B$10 | I18: =Assumptions!$B$9-SUM($H$4:H18) | J18: =YEAR(B18)
A19: 16 | B19: =EOMONTH(Assumptions!$B$3,15) | C19: =G18 | D19: =C19*Assumptions!$B$7 | E19: =Assumptions!$B$4 | F19: =E19-D19 | G19: =C19-F19 | H19: =Assumptions!$B$10 | I19: =Assumptions!$B$9-SUM($H$4:H19) | J19: =YEAR(B19)
A20: 17 | B20: =EOMONTH(Assumptions!$B$3,16) | C20: =G19 | D20: =C20*Assumptions!$B$7 | E20: =Assumptions!$B$4 | F20: =E20-D20 | G20: =C20-F20 | H20: =Assumptions!$B$10 | I20: =Assumptions!$B$9-SUM($H$4:H20) | J20: =YEAR(B20)
A21: 18 | B21: =EOMONTH(Assumptions!$B$3,17) | C21: =G20 | D21: =C21*Assumptions!$B$7 | E21: =Assumptions!$B$4 | F21: =E21-D21 | G21: =C21-F21 | H21: =Assumptions!$B$10 | I21: =Assumptions!$B$9-SUM($H$4:H21) | J21: =YEAR(B21)
A22: 19 | B22: =EOMONTH(Assumptions!$B$3,18) | C22: =G21 | D22: =C22*Assumptions!$B$7 | E22: =Assumptions!$B$4 | F22: =E22-D22 | G22: =C22-F22 | H22: =Assumptions!$B$10 | I22: =Assumptions!$B$9-SUM($H$4:H22) | J22: =YEAR(B22)
A23: 20 | B23: =EOMONTH(Assumptions!$B$3,19) | C23: =G22 | D23: =C23*Assumptions!$B$7 | E23: =Assumptions!$B$4 | F23: =E23-D23 | G23: =C23-F23 | H23: =Assumptions!$B$10 | I23: =Assumptions!$B$9-SUM($H$4:H23) | J23: =YEAR(B23)
A24: 21 | B24: =EOMONTH(Assumptions!$B$3,20) | C24: =G23 | D24: =C24*Assumptions!$B$7 | E24: =Assumptions!$B$4 | F24: =E24-D24 | G24: =C24-F24 | H24: =Assumptions!$B$10 | I24: =Assumptions!$B$9-SUM($H$4:H24) | J24: =YEAR(B24)
A25: 22 | B25: =EOMONTH(Assumptions!$B$3,21) | C25: =G24 | D25: =C25*Assumptions!$B$7 | E25: =Assumptions!$B$4 | F25: =E25-D25 | G25: =C25-F25 | H25: =Assumptions!$B$10 | I25: =Assumptions!$B$9-SUM($H$4:H25) | J25: =YEAR(B25)
A26: 23 | B26: =EOMONTH(Assumptions!$B$3,22) | C26: =G25 | D26: =C26*Assumptions!$B$7 | E26: =Assumptions!$B$4 | F26: =E26-D26 | G26: =C26-F26 | H26: =Assumptions!$B$10 | I26: =Assumptions!$B$9-SUM($H$4:H26) | J26: =YEAR(B26)
A27: 24 | B27: =EOMONTH(Assumptions!$B$3,23) | C27: =G26 | D27: =C27*Assumptions!$B$7 | E27: =Assumptions!$B$4 | F27: =E27-D27 | G27: =C27-F27 | H27: =Assumptions!$B$10 | I27: =Assumptions!$B$9-SUM($H$4:H27) | J27: =YEAR(B27)
A28: 合计 | D28: =SUM(D4:D27) | E28: =SUM(E4:E27) | F28: =SUM(F4:F27) | H28: =SUM(H4:H27)

Sheet Annual Summary
A1: 年度汇总（SUMIFS 按 Year 列；元）
A2: Year | B2: Interest Expense | C2: Cash Payments | D2: ROU Depreciation | E2: Total P&L Charge (Interest + Depreciation) | F2: Closing Lease Liability (year-end) | G2: Closing ROU (year-end)
A3: 2027 | B3: =SUMIFS(Schedule!$D$4:$D$27,Schedule!$J$4:$J$27,A3) | C3: =SUMIFS(Schedule!$E$4:$E$27,Schedule!$J$4:$J$27,A3) | D3: =SUMIFS(Schedule!$H$4:$H$27,Schedule!$J$4:$J$27,A3) | E3: =B3+D3 | F3: =INDEX(Schedule!$G$4:$G$27,MATCH(A3,Schedule!$J$4:$J$27,1)) | G3: =INDEX(Schedule!$I$4:$I$27,MATCH(A3,Schedule!$J$4:$J$27,1))
A4: 2028 | B4: =SUMIFS(Schedule!$D$4:$D$27,Schedule!$J$4:$J$27,A4) | C4: =SUMIFS(Schedule!$E$4:$E$27,Schedule!$J$4:$J$27,A4) | D4: =SUMIFS(Schedule!$H$4:$H$27,Schedule!$J$4:$J$27,A4) | E4: =B4+D4 | F4: =INDEX(Schedule!$G$4:$G$27,MATCH(A4,Schedule!$J$4:$J$27,1)) | G4: =INDEX(Schedule!$I$4:$I$27,MATCH(A4,Schedule!$J$4:$J$27,1))
A5: 合计 | B5: =SUM(B3:B4) | C5: =SUM(C3:C4) | D5: =SUM(D3:D4) | E5: =SUM(E3:E4)
A7: MATCH(...,1) 取该年度最后一行（Year 列升序）。

Sheet Checks
A1: 检查项 | B1: 结果 | C1: 差异值
A2: 第 24 月期末负债 ≈ 0（容差 1 元） | B2: =ABS(Schedule!G27)<1 | C2: =Schedule!G27
A3: 付款合计 = 初始负债 + 利息合计 | B3: =ABS(Schedule!E28-(Assumptions!B8+Schedule!D28))<1 | C3: =Schedule!E28-(Assumptions!B8+Schedule!D28)
A4: 本金合计 = 初始负债 | B4: =ABS(Schedule!F28-Assumptions!B8)<1 | C4: =Schedule!F28-Assumptions!B8
A5: 折旧合计 = ROU 初始值 | B5: =ABS(Schedule!H28-Assumptions!B9)<1 | C5: =Schedule!H28-Assumptions!B9
A6: 第 24 月 ROU 账面 ≈ 0 | B6: =ABS(Schedule!I27)<1 | C6: =Schedule!I27
A7: (1+月率)^12 = 1.06 | B7: =ABS((1+Assumptions!B7)^12-1.06)<0.0000001 | C7: =(1+Assumptions!B7)^12-1.06
A8: 年度利息合计 = 摊销表利息合计 | B8: =ABS('Annual Summary'!B5-Schedule!D28)<1 | C8: ='Annual Summary'!B5-Schedule!D28
