Workbook

Sheet Assumptions
A1: 假设（百万元；黄色=输入）
A3: 期初现金 | B3: 2
A4: 变动成本率（占收入） | B4: 0.32
A5: 最低现金余额 | B5: 0.8
A6: 下行情景收入下降幅度 | B6: 0.15
A7: 收入收现比例（当月） | B7: 1
A10: 月份 | B10: M1 | C10: M2 | D10: M3 | E10: M4 | F10: M5 | G10: M6
A11: 收入 | B11: 1.2 | C11: 1.3 | D11: 1.5 | E11: 1.4 | F11: 1.6 | G11: 1.8
A12: 固定费用 | B12: 0.75 | C12: 0.75 | D12: 0.75 | E12: 0.75 | F12: 0.75 | G12: 0.75
A13: 资本开支 | B13: 0.2 | C13: 0 | D13: 0.5 | E13: 0 | F13: 0.3 | G13: 0
A14: 融资流入 | B14: 0 | C14: 0.5 | D14: 0 | E14: 0 | F14: 0 | G14: 0
A16: 题内规则：收入当月全额收现；变动成本 = 收入×32%；下行情景仅收入 −15%，变动成本随收入变化；月末现金不得低于 0.8。

Sheet Base
A1: Base 情景现金流（百万元，保留三位小数；全部为公式）
A2: 项目 | B2: M1 | C2: M2 | D2: M3 | E2: M4 | F2: M5 | G2: M6
A3: 收入 | B3: =Assumptions!B11*Assumptions!$B$7 | C3: =Assumptions!C11*Assumptions!$B$7 | D3: =Assumptions!D11*Assumptions!$B$7 | E3: =Assumptions!E11*Assumptions!$B$7 | F3: =Assumptions!F11*Assumptions!$B$7 | G3: =Assumptions!G11*Assumptions!$B$7
A4: 变动成本 | B4: =-B3*Assumptions!$B$4 | C4: =-C3*Assumptions!$B$4 | D4: =-D3*Assumptions!$B$4 | E4: =-E3*Assumptions!$B$4 | F4: =-F3*Assumptions!$B$4 | G4: =-G3*Assumptions!$B$4
A5: 固定费用 | B5: =-Assumptions!B12 | C5: =-Assumptions!C12 | D5: =-Assumptions!D12 | E5: =-Assumptions!E12 | F5: =-Assumptions!F12 | G5: =-Assumptions!G12
A6: 资本开支 | B6: =-Assumptions!B13 | C6: =-Assumptions!C13 | D6: =-Assumptions!D13 | E6: =-Assumptions!E13 | F6: =-Assumptions!F13 | G6: =-Assumptions!G13
A7: 融资流入 | B7: =Assumptions!B14 | C7: =Assumptions!C14 | D7: =Assumptions!D14 | E7: =Assumptions!E14 | F7: =Assumptions!F14 | G7: =Assumptions!G14
A8: 净现金流 | B8: =SUM(B3:B7) | C8: =SUM(C3:C7) | D8: =SUM(D3:D7) | E8: =SUM(E3:E7) | F8: =SUM(F3:F7) | G8: =SUM(G3:G7)
A9: 期初现金 | B9: =Assumptions!$B$3 | C9: =B10 | D9: =C10 | E9: =D10 | F9: =E10 | G9: =F10
A10: 期末现金 | B10: =B9+B8 | C10: =C9+C8 | D10: =D9+D8 | E10: =E9+E8 | F10: =F9+F8 | G10: =G9+G8
A11: 最低现金检查 | B11: =IF(B10>=Assumptions!$B$5,"OK","BREACH") | C11: =IF(C10>=Assumptions!$B$5,"OK","BREACH") | D11: =IF(D10>=Assumptions!$B$5,"OK","BREACH") | E11: =IF(E10>=Assumptions!$B$5,"OK","BREACH") | F11: =IF(F10>=Assumptions!$B$5,"OK","BREACH") | G11: =IF(G10>=Assumptions!$B$5,"OK","BREACH")
A12: 高于最低线余量 | B12: =B10-Assumptions!$B$5 | C12: =C10-Assumptions!$B$5 | D12: =D10-Assumptions!$B$5 | E12: =E10-Assumptions!$B$5 | F12: =F10-Assumptions!$B$5 | G12: =G10-Assumptions!$B$5
A14: 最低期末现金 | B14: =MIN(B10:G10)
A15: 最低现金出现月份 | B15: =INDEX($B$2:$G$2,MATCH(B14,$B$10:$G$10,0))
A16: 六个月累计净现金流 | B16: =SUM(B8:G8)
A17: 勾稽：期初 + 累计净现金流 − M6 期末（应为 0） | B17: =Assumptions!B3+B16-G10

Sheet Downside
A1: Downside 情景现金流（百万元，保留三位小数；全部为公式）
A2: 项目 | B2: M1 | C2: M2 | D2: M3 | E2: M4 | F2: M5 | G2: M6
A3: 收入 | B3: =Assumptions!B11*(1-Assumptions!$B$6)*Assumptions!$B$7 | C3: =Assumptions!C11*(1-Assumptions!$B$6)*Assumptions!$B$7 | D3: =Assumptions!D11*(1-Assumptions!$B$6)*Assumptions!$B$7 | E3: =Assumptions!E11*(1-Assumptions!$B$6)*Assumptions!$B$7 | F3: =Assumptions!F11*(1-Assumptions!$B$6)*Assumptions!$B$7 | G3: =Assumptions!G11*(1-Assumptions!$B$6)*Assumptions!$B$7
A4: 变动成本 | B4: =-B3*Assumptions!$B$4 | C4: =-C3*Assumptions!$B$4 | D4: =-D3*Assumptions!$B$4 | E4: =-E3*Assumptions!$B$4 | F4: =-F3*Assumptions!$B$4 | G4: =-G3*Assumptions!$B$4
A5: 固定费用 | B5: =-Assumptions!B12 | C5: =-Assumptions!C12 | D5: =-Assumptions!D12 | E5: =-Assumptions!E12 | F5: =-Assumptions!F12 | G5: =-Assumptions!G12
A6: 资本开支 | B6: =-Assumptions!B13 | C6: =-Assumptions!C13 | D6: =-Assumptions!D13 | E6: =-Assumptions!E13 | F6: =-Assumptions!F13 | G6: =-Assumptions!G13
A7: 融资流入 | B7: =Assumptions!B14 | C7: =Assumptions!C14 | D7: =Assumptions!D14 | E7: =Assumptions!E14 | F7: =Assumptions!F14 | G7: =Assumptions!G14
A8: 净现金流 | B8: =SUM(B3:B7) | C8: =SUM(C3:C7) | D8: =SUM(D3:D7) | E8: =SUM(E3:E7) | F8: =SUM(F3:F7) | G8: =SUM(G3:G7)
A9: 期初现金 | B9: =Assumptions!$B$3 | C9: =B10 | D9: =C10 | E9: =D10 | F9: =E10 | G9: =F10
A10: 期末现金 | B10: =B9+B8 | C10: =C9+C8 | D10: =D9+D8 | E10: =E9+E8 | F10: =F9+F8 | G10: =G9+G8
A11: 最低现金检查 | B11: =IF(B10>=Assumptions!$B$5,"OK","BREACH") | C11: =IF(C10>=Assumptions!$B$5,"OK","BREACH") | D11: =IF(D10>=Assumptions!$B$5,"OK","BREACH") | E11: =IF(E10>=Assumptions!$B$5,"OK","BREACH") | F11: =IF(F10>=Assumptions!$B$5,"OK","BREACH") | G11: =IF(G10>=Assumptions!$B$5,"OK","BREACH")
A12: 高于最低线余量 | B12: =B10-Assumptions!$B$5 | C12: =C10-Assumptions!$B$5 | D12: =D10-Assumptions!$B$5 | E12: =E10-Assumptions!$B$5 | F12: =F10-Assumptions!$B$5 | G12: =G10-Assumptions!$B$5
A14: 最低期末现金 | B14: =MIN(B10:G10)
A15: 最低现金出现月份 | B15: =INDEX($B$2:$G$2,MATCH(B14,$B$10:$G$10,0))
A16: 六个月累计净现金流 | B16: =SUM(B8:G8)
A17: 勾稽：期初 + 累计净现金流 − M6 期末（应为 0） | B17: =Assumptions!B3+B16-G10

Sheet Dashboard
A1: Dashboard（全部引用 Base / Downside / Assumptions）
A2: 指标 | B2: Base | C2: Downside | D2: 差异（Downside − Base）
A3: 最低期末现金 | B3: =Base!B14 | C3: =Downside!B14 | D3: =C3-B3
A4: 最低现金月份 | B4: =Base!B15 | C4: =Downside!B15
A5: M6 期末现金 | B5: =Base!G10 | C5: =Downside!G10 | D5: =C5-B5
A6: 六个月累计净现金流 | B6: =Base!B16 | C6: =Downside!B16 | D6: =C6-B6
A7: 六个月收入合计 | B7: =SUM(Base!B3:G3) | C7: =SUM(Downside!B3:G3) | D7: =C7-B7
A8: 最低线 0.8 是否守住 | B8: =IF(COUNTIF(Base!B11:G11,"BREACH")=0,"是","否") | C8: =IF(COUNTIF(Downside!B11:G11,"BREACH")=0,"是","否")
A9: 最低余量（最低现金 − 0.8） | B9: =Base!B14-Assumptions!B5 | C9: =Downside!B14-Assumptions!B5 | D9: =C9-B9
A12: 月份 | B12: Base 期末现金 | C12: Downside 期末现金 | D12: 最低线
A13: M1 | B13: =Base!B10 | C13: =Downside!B10 | D13: =Assumptions!$B$5
A14: M2 | B14: =Base!C10 | C14: =Downside!C10 | D14: =Assumptions!$B$5
A15: M3 | B15: =Base!D10 | C15: =Downside!D10 | D15: =Assumptions!$B$5
A16: M4 | B16: =Base!E10 | C16: =Downside!E10 | D16: =Assumptions!$B$5
A17: M5 | B17: =Base!F10 | C17: =Downside!F10 | D17: =Assumptions!$B$5
A18: M6 | B18: =Base!G10 | C18: =Downside!G10 | D18: =Assumptions!$B$5
A21: 可承受的最大统一收入下降幅度（守住 0.8 最低线）
A22: 月份 | B22: 累计收入（Base） | C22: 累计(固定+资本开支−融资) | D22: 该月约束下的最大下降幅度 | E22: 说明
A23: M1 | B23: =SUM(Assumptions!$B$11:B11) | C23: =SUM(Assumptions!$B$12:B12)+SUM(Assumptions!$B$13:B13)-SUM(Assumptions!$B$14:B14) | D23: =1-(Assumptions!$B$5-Assumptions!$B$3+C23)/((1-Assumptions!$B$4)*B23) | E23: 推导：期末现金_m = 期初 + (1−32%)×累计收入×(1−d) − 累计(固定+资本开支−融资) ≥ 0.8 ⇒ d ≤ 1 − (0.8 − 期初 + 累计支出净额)/((1−32%)×累计收入)
A24: M2 | B24: =SUM(Assumptions!$B$11:C11) | C24: =SUM(Assumptions!$B$12:C12)+SUM(Assumptions!$B$13:C13)-SUM(Assumptions!$B$14:C14) | D24: =1-(Assumptions!$B$5-Assumptions!$B$3+C24)/((1-Assumptions!$B$4)*B24)
A25: M3 | B25: =SUM(Assumptions!$B$11:D11) | C25: =SUM(Assumptions!$B$12:D12)+SUM(Assumptions!$B$13:D13)-SUM(Assumptions!$B$14:D14) | D25: =1-(Assumptions!$B$5-Assumptions!$B$3+C25)/((1-Assumptions!$B$4)*B25)
A26: M4 | B26: =SUM(Assumptions!$B$11:E11) | C26: =SUM(Assumptions!$B$12:E12)+SUM(Assumptions!$B$13:E13)-SUM(Assumptions!$B$14:E14) | D26: =1-(Assumptions!$B$5-Assumptions!$B$3+C26)/((1-Assumptions!$B$4)*B26)
A27: M5 | B27: =SUM(Assumptions!$B$11:F11) | C27: =SUM(Assumptions!$B$12:F12)+SUM(Assumptions!$B$13:F13)-SUM(Assumptions!$B$14:F14) | D27: =1-(Assumptions!$B$5-Assumptions!$B$3+C27)/((1-Assumptions!$B$4)*B27)
A28: M6 | B28: =SUM(Assumptions!$B$11:G11) | C28: =SUM(Assumptions!$B$12:G12)+SUM(Assumptions!$B$13:G13)-SUM(Assumptions!$B$14:G14) | D28: =1-(Assumptions!$B$5-Assumptions!$B$3+C28)/((1-Assumptions!$B$4)*B28)
A30: 最大可承受下降幅度（各月约束取最小） | D30: =MIN(D23:D28)
A31: 约束月份 | D31: =INDEX(A23:A28,MATCH(D30,D23:D28,0))
A34: 敏感性：统一收入下降幅度 → 最低期末现金（公式）
A35: 下降幅度 | B35: 最低期末现金 | C35: 是否守住 0.8
A36: 0 | B36: =MIN(Assumptions!$B$3+(1-Assumptions!$B$4)*(1-$A36)*SUM(Assumptions!$B$11:B11)-SUM(Assumptions!$B$12:B12)-SUM(Assumptions!$B$13:B13)+SUM(Assumptions!$B$14:B14),Assumptions!$B$3+(1-Assumptions!$B$4)*(1-$A36)*SUM(Assumptions!$B$11:C11)-SUM(Assumptions!$B$12:C12)-SUM(Assumptions!$B$13:C13)+SUM(Assumptions!$B$14:C14),Assumptions!$B$3+(1-Assumptions!$B$4)*(1-$A36)*SUM(Assumptions!$B$11:D11)-SUM(Assumptions!$B$12:D12)-SUM(Assumptions!$B$13:D13)+SUM(Assumptions!$B$14:D14),Assumptions!$B$3+(1-Assumptions!$B$4)*(1-$A36)*SUM(Assumptions!$B$11:E11)-SUM(Assumptions!$B$12:E12)-SUM(Assumptions!$B$13:E13)+SUM(Assumptions!$B$14:E14),Assumptions!$B$3+(1-Assumptions!$B$4)*(1-$A36)*SUM(Assumptions!$B$11:F11)-SUM(Assumptions!$B$12:F12)-SUM(Assumptions!$B$13:F13)+SUM(Assumptions!$B$14:F14),Assumptions!$B$3+(1-Assumptions!$B$4)*(1-$A36)*SUM(Assumptions!$B$11:G11)-SUM(Assumptions!$B$12:G12)-SUM(Assumptions!$B$13:G13)+SUM(Assumptions!$B$14:G14)) | C36: =IF(B36>=Assumptions!$B$5,"是","否")
A37: 0.05 | B37: =MIN(Assumptions!$B$3+(1-Assumptions!$B$4)*(1-$A37)*SUM(Assumptions!$B$11:B11)-SUM(Assumptions!$B$12:B12)-SUM(Assumptions!$B$13:B13)+SUM(Assumptions!$B$14:B14),Assumptions!$B$3+(1-Assumptions!$B$4)*(1-$A37)*SUM(Assumptions!$B$11:C11)-SUM(Assumptions!$B$12:C12)-SUM(Assumptions!$B$13:C13)+SUM(Assumptions!$B$14:C14),Assumptions!$B$3+(1-Assumptions!$B$4)*(1-$A37)*SUM(Assumptions!$B$11:D11)-SUM(Assumptions!$B$12:D12)-SUM(Assumptions!$B$13:D13)+SUM(Assumptions!$B$14:D14),Assumptions!$B$3+(1-Assumptions!$B$4)*(1-$A37)*SUM(Assumptions!$B$11:E11)-SUM(Assumptions!$B$12:E12)-SUM(Assumptions!$B$13:E13)+SUM(Assumptions!$B$14:E14),Assumptions!$B$3+(1-Assumptions!$B$4)*(1-$A37)*SUM(Assumptions!$B$11:F11)-SUM(Assumptions!$B$12:F12)-SUM(Assumptions!$B$13:F13)+SUM(Assumptions!$B$14:F14),Assumptions!$B$3+(1-Assumptions!$B$4)*(1-$A37)*SUM(Assumptions!$B$11:G11)-SUM(Assumptions!$B$12:G12)-SUM(Assumptions!$B$13:G13)+SUM(Assumptions!$B$14:G14)) | C37: =IF(B37>=Assumptions!$B$5,"是","否")
A38: 0.1 | B38: =MIN(Assumptions!$B$3+(1-Assumptions!$B$4)*(1-$A38)*SUM(Assumptions!$B$11:B11)-SUM(Assumptions!$B$12:B12)-SUM(Assumptions!$B$13:B13)+SUM(Assumptions!$B$14:B14),Assumptions!$B$3+(1-Assumptions!$B$4)*(1-$A38)*SUM(Assumptions!$B$11:C11)-SUM(Assumptions!$B$12:C12)-SUM(Assumptions!$B$13:C13)+SUM(Assumptions!$B$14:C14),Assumptions!$B$3+(1-Assumptions!$B$4)*(1-$A38)*SUM(Assumptions!$B$11:D11)-SUM(Assumptions!$B$12:D12)-SUM(Assumptions!$B$13:D13)+SUM(Assumptions!$B$14:D14),Assumptions!$B$3+(1-Assumptions!$B$4)*(1-$A38)*SUM(Assumptions!$B$11:E11)-SUM(Assumptions!$B$12:E12)-SUM(Assumptions!$B$13:E13)+SUM(Assumptions!$B$14:E14),Assumptions!$B$3+(1-Assumptions!$B$4)*(1-$A38)*SUM(Assumptions!$B$11:F11)-SUM(Assumptions!$B$12:F12)-SUM(Assumptions!$B$13:F13)+SUM(Assumptions!$B$14:F14),Assumptions!$B$3+(1-Assumptions!$B$4)*(1-$A38)*SUM(Assumptions!$B$11:G11)-SUM(Assumptions!$B$12:G12)-SUM(Assumptions!$B$13:G13)+SUM(Assumptions!$B$14:G14)) | C38: =IF(B38>=Assumptions!$B$5,"是","否")
A39: 0.15 | B39: =MIN(Assumptions!$B$3+(1-Assumptions!$B$4)*(1-$A39)*SUM(Assumptions!$B$11:B11)-SUM(Assumptions!$B$12:B12)-SUM(Assumptions!$B$13:B13)+SUM(Assumptions!$B$14:B14),Assumptions!$B$3+(1-Assumptions!$B$4)*(1-$A39)*SUM(Assumptions!$B$11:C11)-SUM(Assumptions!$B$12:C12)-SUM(Assumptions!$B$13:C13)+SUM(Assumptions!$B$14:C14),Assumptions!$B$3+(1-Assumptions!$B$4)*(1-$A39)*SUM(Assumptions!$B$11:D11)-SUM(Assumptions!$B$12:D12)-SUM(Assumptions!$B$13:D13)+SUM(Assumptions!$B$14:D14),Assumptions!$B$3+(1-Assumptions!$B$4)*(1-$A39)*SUM(Assumptions!$B$11:E11)-SUM(Assumptions!$B$12:E12)-SUM(Assumptions!$B$13:E13)+SUM(Assumptions!$B$14:E14),Assumptions!$B$3+(1-Assumptions!$B$4)*(1-$A39)*SUM(Assumptions!$B$11:F11)-SUM(Assumptions!$B$12:F12)-SUM(Assumptions!$B$13:F13)+SUM(Assumptions!$B$14:F14),Assumptions!$B$3+(1-Assumptions!$B$4)*(1-$A39)*SUM(Assumptions!$B$11:G11)-SUM(Assumptions!$B$12:G12)-SUM(Assumptions!$B$13:G13)+SUM(Assumptions!$B$14:G14)) | C39: =IF(B39>=Assumptions!$B$5,"是","否")
A40: 0.2 | B40: =MIN(Assumptions!$B$3+(1-Assumptions!$B$4)*(1-$A40)*SUM(Assumptions!$B$11:B11)-SUM(Assumptions!$B$12:B12)-SUM(Assumptions!$B$13:B13)+SUM(Assumptions!$B$14:B14),Assumptions!$B$3+(1-Assumptions!$B$4)*(1-$A40)*SUM(Assumptions!$B$11:C11)-SUM(Assumptions!$B$12:C12)-SUM(Assumptions!$B$13:C13)+SUM(Assumptions!$B$14:C14),Assumptions!$B$3+(1-Assumptions!$B$4)*(1-$A40)*SUM(Assumptions!$B$11:D11)-SUM(Assumptions!$B$12:D12)-SUM(Assumptions!$B$13:D13)+SUM(Assumptions!$B$14:D14),Assumptions!$B$3+(1-Assumptions!$B$4)*(1-$A40)*SUM(Assumptions!$B$11:E11)-SUM(Assumptions!$B$12:E12)-SUM(Assumptions!$B$13:E13)+SUM(Assumptions!$B$14:E14),Assumptions!$B$3+(1-Assumptions!$B$4)*(1-$A40)*SUM(Assumptions!$B$11:F11)-SUM(Assumptions!$B$12:F12)-SUM(Assumptions!$B$13:F13)+SUM(Assumptions!$B$14:F14),Assumptions!$B$3+(1-Assumptions!$B$4)*(1-$A40)*SUM(Assumptions!$B$11:G11)-SUM(Assumptions!$B$12:G12)-SUM(Assumptions!$B$13:G13)+SUM(Assumptions!$B$14:G14)) | C40: =IF(B40>=Assumptions!$B$5,"是","否")
A41: 0.25 | B41: =MIN(Assumptions!$B$3+(1-Assumptions!$B$4)*(1-$A41)*SUM(Assumptions!$B$11:B11)-SUM(Assumptions!$B$12:B12)-SUM(Assumptions!$B$13:B13)+SUM(Assumptions!$B$14:B14),Assumptions!$B$3+(1-Assumptions!$B$4)*(1-$A41)*SUM(Assumptions!$B$11:C11)-SUM(Assumptions!$B$12:C12)-SUM(Assumptions!$B$13:C13)+SUM(Assumptions!$B$14:C14),Assumptions!$B$3+(1-Assumptions!$B$4)*(1-$A41)*SUM(Assumptions!$B$11:D11)-SUM(Assumptions!$B$12:D12)-SUM(Assumptions!$B$13:D13)+SUM(Assumptions!$B$14:D14),Assumptions!$B$3+(1-Assumptions!$B$4)*(1-$A41)*SUM(Assumptions!$B$11:E11)-SUM(Assumptions!$B$12:E12)-SUM(Assumptions!$B$13:E13)+SUM(Assumptions!$B$14:E14),Assumptions!$B$3+(1-Assumptions!$B$4)*(1-$A41)*SUM(Assumptions!$B$11:F11)-SUM(Assumptions!$B$12:F12)-SUM(Assumptions!$B$13:F13)+SUM(Assumptions!$B$14:F14),Assumptions!$B$3+(1-Assumptions!$B$4)*(1-$A41)*SUM(Assumptions!$B$11:G11)-SUM(Assumptions!$B$12:G12)-SUM(Assumptions!$B$13:G13)+SUM(Assumptions!$B$14:G14)) | C41: =IF(B41>=Assumptions!$B$5,"是","否")
A42: 0.3 | B42: =MIN(Assumptions!$B$3+(1-Assumptions!$B$4)*(1-$A42)*SUM(Assumptions!$B$11:B11)-SUM(Assumptions!$B$12:B12)-SUM(Assumptions!$B$13:B13)+SUM(Assumptions!$B$14:B14),Assumptions!$B$3+(1-Assumptions!$B$4)*(1-$A42)*SUM(Assumptions!$B$11:C11)-SUM(Assumptions!$B$12:C12)-SUM(Assumptions!$B$13:C13)+SUM(Assumptions!$B$14:C14),Assumptions!$B$3+(1-Assumptions!$B$4)*(1-$A42)*SUM(Assumptions!$B$11:D11)-SUM(Assumptions!$B$12:D12)-SUM(Assumptions!$B$13:D13)+SUM(Assumptions!$B$14:D14),Assumptions!$B$3+(1-Assumptions!$B$4)*(1-$A42)*SUM(Assumptions!$B$11:E11)-SUM(Assumptions!$B$12:E12)-SUM(Assumptions!$B$13:E13)+SUM(Assumptions!$B$14:E14),Assumptions!$B$3+(1-Assumptions!$B$4)*(1-$A42)*SUM(Assumptions!$B$11:F11)-SUM(Assumptions!$B$12:F12)-SUM(Assumptions!$B$13:F13)+SUM(Assumptions!$B$14:F14),Assumptions!$B$3+(1-Assumptions!$B$4)*(1-$A42)*SUM(Assumptions!$B$11:G11)-SUM(Assumptions!$B$12:G12)-SUM(Assumptions!$B$13:G13)+SUM(Assumptions!$B$14:G14)) | C42: =IF(B42>=Assumptions!$B$5,"是","否")
A43: 0.35 | B43: =MIN(Assumptions!$B$3+(1-Assumptions!$B$4)*(1-$A43)*SUM(Assumptions!$B$11:B11)-SUM(Assumptions!$B$12:B12)-SUM(Assumptions!$B$13:B13)+SUM(Assumptions!$B$14:B14),Assumptions!$B$3+(1-Assumptions!$B$4)*(1-$A43)*SUM(Assumptions!$B$11:C11)-SUM(Assumptions!$B$12:C12)-SUM(Assumptions!$B$13:C13)+SUM(Assumptions!$B$14:C14),Assumptions!$B$3+(1-Assumptions!$B$4)*(1-$A43)*SUM(Assumptions!$B$11:D11)-SUM(Assumptions!$B$12:D12)-SUM(Assumptions!$B$13:D13)+SUM(Assumptions!$B$14:D14),Assumptions!$B$3+(1-Assumptions!$B$4)*(1-$A43)*SUM(Assumptions!$B$11:E11)-SUM(Assumptions!$B$12:E12)-SUM(Assumptions!$B$13:E13)+SUM(Assumptions!$B$14:E14),Assumptions!$B$3+(1-Assumptions!$B$4)*(1-$A43)*SUM(Assumptions!$B$11:F11)-SUM(Assumptions!$B$12:F12)-SUM(Assumptions!$B$13:F13)+SUM(Assumptions!$B$14:F14),Assumptions!$B$3+(1-Assumptions!$B$4)*(1-$A43)*SUM(Assumptions!$B$11:G11)-SUM(Assumptions!$B$12:G12)-SUM(Assumptions!$B$13:G13)+SUM(Assumptions!$B$14:G14)) | C43: =IF(B43>=Assumptions!$B$5,"是","否")
A44: 0.4 | B44: =MIN(Assumptions!$B$3+(1-Assumptions!$B$4)*(1-$A44)*SUM(Assumptions!$B$11:B11)-SUM(Assumptions!$B$12:B12)-SUM(Assumptions!$B$13:B13)+SUM(Assumptions!$B$14:B14),Assumptions!$B$3+(1-Assumptions!$B$4)*(1-$A44)*SUM(Assumptions!$B$11:C11)-SUM(Assumptions!$B$12:C12)-SUM(Assumptions!$B$13:C13)+SUM(Assumptions!$B$14:C14),Assumptions!$B$3+(1-Assumptions!$B$4)*(1-$A44)*SUM(Assumptions!$B$11:D11)-SUM(Assumptions!$B$12:D12)-SUM(Assumptions!$B$13:D13)+SUM(Assumptions!$B$14:D14),Assumptions!$B$3+(1-Assumptions!$B$4)*(1-$A44)*SUM(Assumptions!$B$11:E11)-SUM(Assumptions!$B$12:E12)-SUM(Assumptions!$B$13:E13)+SUM(Assumptions!$B$14:E14),Assumptions!$B$3+(1-Assumptions!$B$4)*(1-$A44)*SUM(Assumptions!$B$11:F11)-SUM(Assumptions!$B$12:F12)-SUM(Assumptions!$B$13:F13)+SUM(Assumptions!$B$14:F14),Assumptions!$B$3+(1-Assumptions!$B$4)*(1-$A44)*SUM(Assumptions!$B$11:G11)-SUM(Assumptions!$B$12:G12)-SUM(Assumptions!$B$13:G13)+SUM(Assumptions!$B$14:G14)) | C44: =IF(B44>=Assumptions!$B$5,"是","否")
