Workbook

Sheet KPI
A1: 经营 KPI（输入=黄色；变化=公式）
A2: 指标 | B2: Q2 | C2: Q1 | D2: Q2 LY | E2: QoQ 变化 | F2: YoY 变化 | G2: 变化口径 | H2: 事实 / 判断
A3: ARR ($m) | B3: 120 | C3: 110 | D3: 95 | E3: =B3/C3-1 | F3: =B3/D3-1 | G3: 百分比（%） | H3: 事实：增长放缓但仍为正
A4: NRR | B4: 1.04 | C4: 1.1 | D4: 1.12 | E4: =B4-C4 | F4: =B4-D4 | G4: 百分点（pp） | H4: 事实：连续两季下降；判断：与上线慢/AI 准确性相关（访谈）
A5: Gross Margin | B5: 0.68 | C5: 0.72 | D5: 0.7 | E5: =B5-C5 | F5: =B5-D5 | G5: 百分点（pp） | H5: 事实：季度 −4pp；原因未知（待 CFO 拆分）
A6: Logo Churn | B6: 0.028 | C6: 0.019 | D6: 0.017 | E6: =B6-C6 | F6: =B6-D6 | G6: 百分点（pp） | H6: 事实：接近翻倍
A7: New Logos | B7: 40 | C7: 55 | D7: 48 | E7: =B7/C7-1 | F7: =B7/D7-1 | G7: 百分比（%） | H7: 事实：新客获取放缓
A8: Cash ($m) | B8: 28 | C8: 31 | D8: 36 | E8: =B8/C8-1 | F8: =B8/D8-1 | G8: 百分比（%） | H8: 事实
A9: Monthly Cash Burn ($m) | B9: 3 | C9: 2.5 | D9: 2.2 | E9: =B9/C9-1 | F9: =B9/D9-1 | G9: 百分比（%） | H9: 事实：烧钱上升
A11: 现金跑道（月）= Cash / Monthly Burn | B11: =B8/B9 | C11: =C8/C9 | D11: =D8/D9
A12: 客户与销售输入
A13: 要求 99.95% SLA 的企业客户数 | B13: 5
A14: 其中愿为高级 SLA 付费 | B14: 2
A15: 当前标准 SLA | B15: 0.999
A16: 流失访谈数 | B16: 10
A17: 提到上线慢 | B17: 6
A18: 提到 AI 摘要准确性 | B18: 3
A19: 提到价格 | B19: 1
A20: AI 模块离线准确率 | B20: 0.88
A21: AI 上线门槛 | B21: 0.92
A22: 现行自动续约通知提前天数 | B22: 30
A23: 两个地区政策要求最少天数 | B23: 60
A24: 方案 1 年成本 ($m) | B24: 0.36
... A28: 方案 3 提价幅度 | B28: 0.08

Sheet Calculations
A1: 自算数据（全部引用 KPI 表）
A2: 计算项 | B2: 公式 | C2: 结果 | D2: 标注
A3: ARR QoQ 增长 | B3: KPI!B3/KPI!C3-1 | C3: =KPI!B3/KPI!C3-1 | D3: 测算
A4: ARR YoY 增长 | B4: KPI!B3/KPI!D3-1 | C4: =KPI!B3/KPI!D3-1 | D4: 测算
A5: NRR QoQ 变化（pp） | B5: KPI!B4-KPI!C4 | C5: =KPI!B4-KPI!C4 | D5: 测算
A6: 毛利率 QoQ 变化（pp） | B6: KPI!B5-KPI!C5 | C6: =KPI!B5-KPI!C5 | D6: 测算
A7: Logo Churn QoQ 变化（pp） | B7: KPI!B6-KPI!C6 | C7: =KPI!B6-KPI!C6 | D7: 测算
A8: 新客数 QoQ 变化 | B8: KPI!B7/KPI!C7-1 | C8: =KPI!B7/KPI!C7-1 | D8: 测算
A9: 现金跑道 Q2（月） | B9: KPI!B8/KPI!B9 | C9: =KPI!B8/KPI!B9 | D9: 测算（简单口径）
A10: 现金跑道 Q1（月） | B10: KPI!C8/KPI!C9 | C10: =KPI!C8/KPI!C9 | D10: 测算
A11: 现金跑道 Q2 LY（月） | B11: KPI!D8/KPI!D9 | C11: =KPI!D8/KPI!D9 | D11: 测算
A12: 流失访谈提到上线慢的比例 | B12: KPI!B17/KPI!B16 | C12: =KPI!B17/KPI!B16 | D12: 事实（10 个访谈）
A13: 提到 AI 准确性的比例 | B13: KPI!B18/KPI!B16 | C13: =KPI!B18/KPI!B16 | D13: 事实
A14: 提到价格的比例 | B14: KPI!B19/KPI!B16 | C14: =KPI!B19/KPI!B16 | D14: 事实
A15: AI 准确率与门槛差距（pp） | B15: KPI!B21-KPI!B20 | C15: =KPI!B21-KPI!B20 | D15: 事实
A16: 续约通知缺口（天） | B16: KPI!B23-KPI!B22 | C16: =KPI!B23-KPI!B22 | D16: 事实
A17: 方案 1 月成本 ($m) | B17: KPI!B24/12 | C17: =KPI!B24/12 | D17: 测算
A18: 方案 1 后月烧钱 ($m) | B18: KPI!B9+C17 | C18: =KPI!B9+C17 | D18: 测算
A19: 方案 1 后跑道（月） | B19: KPI!B8/C18 | C19: =KPI!B8/C18 | D19: 测算
A20: 方案 1 上线期缩短 | B20: 1-KPI!B26/KPI!B25 | C20: =1-KPI!B26/KPI!B25 | D20: 管理层估计，未经试点
A21: 方案 1+2 后跑道（月） | B21: (KPI!B8-KPI!B27)/C18 | C21: =(KPI!B8-KPI!B27)/C18 | D21: 测算：一次性 0.25 从现金扣除
A22: 方案 3 理论年化毛增量 ($m) | B22: KPI!B3*KPI!B28 | C22: =KPI!B3*KPI!B28 | D22: 测算，未考虑流失/折扣/时点
A23: 方案 3 盈亏平衡额外流失率 | B23: 1-1/(1+KPI!B28) | C23: =1-1/(1+KPI!B28) | D23: 测算：1.08×(1−c)=1

Sheet Decision Scenarios
A1: 决定 3：全体提价 8% 的流失弹性情景（ARR $m；公式）
A2: 额外流失率 c | B2: 提价后 ARR = ARR×(1+8%)×(1−c) | C2: 净变化 vs 当前 ARR | D2: 净变化 % | E2: 判断
A3: 0 | B3: =KPI!$B$3*(1+KPI!$B$28)*(1-A3) | C3: =B3-KPI!$B$3 | D3: =C3/KPI!$B$3 | E3: =IF(C3>0,"正增量","无增量/负增量")
A4: 0.02 | B4: =KPI!$B$3*(1+KPI!$B$28)*(1-A4) | C4: =B4-KPI!$B$3 | D4: =C4/KPI!$B$3 | E4: =IF(C4>0,"正增量","无增量/负增量")
A5: 0.04 | B5: =KPI!$B$3*(1+KPI!$B$28)*(1-A5) | C5: =B5-KPI!$B$3 | D5: =C5/KPI!$B$3 | E5: =IF(C5>0,"正增量","无增量/负增量")
A6: 0.06 | B6: =KPI!$B$3*(1+KPI!$B$28)*(1-A6) | C6: =B6-KPI!$B$3 | D6: =C6/KPI!$B$3 | E6: =IF(C6>0,"正增量","无增量/负增量")
A7: 0.0741 | B7: =KPI!$B$3*(1+KPI!$B$28)*(1-A7) | C7: =B7-KPI!$B$3 | D7: =C7/KPI!$B$3 | E7: =IF(C7>0,"正增量","无增量/负增量")
A8: 0.1 | B8: =KPI!$B$3*(1+KPI!$B$28)*(1-A8) | C8: =B8-KPI!$B$3 | D8: =C8/KPI!$B$3 | E8: =IF(C8>0,"正增量","无增量/负增量")
A9: 0.15 | B9: =KPI!$B$3*(1+KPI!$B$28)*(1-A9) | C9: =B9-KPI!$B$3 | D9: =C9/KPI!$B$3 | E9: =IF(C9>0,"正增量","无增量/负增量")
A11: 解读：当前季度 Logo Churn 已从 1.9% 升至 2.8%，NRR 降至 104%；提价触发的额外流失只需超过 7.4% 即抹平全部理论增量。销售方案未提供流失弹性分析，因此不建议全体提价。
A15: 决定 1：增加 2 名上线经理（$m）
A16: 项目 | B16: 数值 | C16: 说明
A17: 年成本 | B17: =KPI!B24 | C17: 事实
A18: 月成本 | B18: =KPI!B24/12 | C18: 测算
A19: 当前月烧钱 | B19: =KPI!B9 | C19: 事实
A20: 方案后月烧钱 | B20: =B18+B19 | C20: 测算
A21: 当前跑道（月） | B21: =KPI!B8/KPI!B9 | C21: 测算
A22: 方案后跑道（月） | B22: =KPI!B8/B20 | C22: 测算
A23: 跑道减少（月） | B23: =B21-B22 | C23: 测算
A24: 上线期 10→7 周 | B24: =1-KPI!B26/KPI!B25 | C24: 管理层估计，未经试点
A25: 流失访谈提到上线慢 | B25: =KPI!B17/KPI!B16 | C25: 事实：6/10
A26: Q2 Logo Churn | B26: =KPI!B6 | C26: 事实
A27: 盈亏平衡：需挽回的 ARR ($m/年) | B27: =KPI!B24 | C27: 测算：挽回 ARR ≥ 年成本即打平（按 ARR 口径，未计毛利）
A28: 对应占 Q2 ARR 比例 | B28: =B27/KPI!B3 | C28: 测算
A31: 决定 2：高级 SLA 产品化（$m）
A32: 项目 | B32: 数值 | C32: 说明
A33: 一次性工程投入 | B33: =KPI!B27 | C33: 事实
A34: 要求 99.95% 的客户数 | B34: =KPI!B13 | C34: 事实
A35: 愿付费客户数 | B35: =KPI!B14 | C35: 事实
A36: 最早上线 | B36: Q4 | C36: 事实
A37: 定价 | B37: 未定 | C37: 未知：不得承诺收入
A38: 方案 1+2 后跑道（月） | B38: =(KPI!B8-KPI!B27)/(KPI!B9+KPI!B24/12) | C38: 测算
A39: 承诺边界 | B39: 在 Q4 上线并定价前，不在合同中承诺 99.95% | C39: 判断/建议
