Workbook

Sheet Assumptions
A1: Item | B1: Value | C1: Excel / note
A2: Start | B2: 2027-01-01 | C2: Month-end payments
A3: N | B3: 24 | C3: periods
A4: Payment | B4: 100000 | C4: in arrears
A5: Annual_rate | B5: 0.06 | C5: effective annual
A6: Monthly_r | B6: =(1+B5)^(1/12)-1 | C6: =(1+6%)^(1/12)-1
A7: Initial_liability | B7: =B4*(1-(1+B6)^-B3)/B6 | C7: PV ordinary annuity
A8: ROU_initial | B8: =B7 | C8: equals liability
A9: Monthly_dep | B9: =B8/B3 | C9: straight line
A10: Display_round | B10: Yuan; keep precision in formulas | C10: do not chain rounded values

Sheet Schedule
A1: Month | B1: Opening_Liability | C1: Interest | D1: Payment | E1: Principal | F1: Closing_Liability | G1: ROU_Depreciation | H1: Year
A2: 1 | B2: =Assumptions!B7 | C2: =B2*Assumptions!$B$6 | D2: =Assumptions!$B$4 | E2: =D2-C2 | F2: =B2+C2-D2 | G2: =Assumptions!$B$9 | H2: 2027
A3: 2 | B3: =F2 | C3: =B3*Assumptions!$B$6 | D3: =Assumptions!$B$4 | E3: =D3-C3 | F3: =B3+C3-D3 | G3: =Assumptions!$B$9 | H3: 2027
A4: 3 | B4: =F3 | C4: =B4*Assumptions!$B$6 | D4: =Assumptions!$B$4 | E4: =D4-C4 | F4: =B4+C4-D4 | G4: =Assumptions!$B$9 | H4: 2027
A5: 4 | B5: =F4 | C5: =B5*Assumptions!$B$6 | D5: =Assumptions!$B$4 | E5: =D5-C5 | F5: =B5+C5-D5 | G5: =Assumptions!$B$9 | H5: 2027
A6: 5 | B6: =F5 | C6: =B6*Assumptions!$B$6 | D6: =Assumptions!$B$4 | E6: =D6-C6 | F6: =B6+C6-D6 | G6: =Assumptions!$B$9 | H6: 2027
A7: 6 | B7: =F6 | C7: =B7*Assumptions!$B$6 | D7: =Assumptions!$B$4 | E7: =D7-C7 | F7: =B7+C7-D7 | G7: =Assumptions!$B$9 | H7: 2027
A8: 7 | B8: =F7 | C8: =B8*Assumptions!$B$6 | D8: =Assumptions!$B$4 | E8: =D8-C8 | F8: =B8+C8-D8 | G8: =Assumptions!$B$9 | H8: 2027
A9: 8 | B9: =F8 | C9: =B9*Assumptions!$B$6 | D9: =Assumptions!$B$4 | E9: =D9-C9 | F9: =B9+C9-D9 | G9: =Assumptions!$B$9 | H9: 2027
A10: 9 | B10: =F9 | C10: =B10*Assumptions!$B$6 | D10: =Assumptions!$B$4 | E10: =D10-C10 | F10: =B10+C10-D10 | G10: =Assumptions!$B$9 | H10: 2027
A11: 10 | B11: =F10 | C11: =B11*Assumptions!$B$6 | D11: =Assumptions!$B$4 | E11: =D11-C11 | F11: =B11+C11-D11 | G11: =Assumptions!$B$9 | H11: 2027
A12: 11 | B12: =F11 | C12: =B12*Assumptions!$B$6 | D12: =Assumptions!$B$4 | E12: =D12-C12 | F12: =B12+C12-D12 | G12: =Assumptions!$B$9 | H12: 2027
A13: 12 | B13: =F12 | C13: =B13*Assumptions!$B$6 | D13: =Assumptions!$B$4 | E13: =D13-C13 | F13: =B13+C13-D13 | G13: =Assumptions!$B$9 | H13: 2027
A14: 13 | B14: =F13 | C14: =B14*Assumptions!$B$6 | D14: =Assumptions!$B$4 | E14: =D14-C14 | F14: =B14+C14-D14 | G14: =Assumptions!$B$9 | H14: 2028
... A25: 24 | B25: =F24 | C25: =B25*Assumptions!$B$6 | D25: =Assumptions!$B$4 | E25: =D25-C25 | F25: =B25+C25-D25 | G25: =Assumptions!$B$9 | H25: 2028
A28: Month 24 closing should be ~0. Internal formulas keep full precision.

Sheet Annual_Summary
A1: Year | B1: Interest | C1: Cash_Payments | D1: Depreciation | E1: Closing_Liability
A2: 2027 | B2: =SUMIF(Schedule!H:H,2027,Schedule!C:C) | C2: =SUMIF(Schedule!H:H,2027,Schedule!D:D) | D2: =SUMIF(Schedule!H:H,2027,Schedule!G:G) | E2: =INDEX(Schedule!F:F,MATCH(12,Schedule!A:A,0))
A3: 2028 | B3: =SUMIF(Schedule!H:H,2028,Schedule!C:C) | C3: =SUMIF(Schedule!H:H,2028,Schedule!D:D) | D3: =SUMIF(Schedule!H:H,2028,Schedule!G:G) | E3: =INDEX(Schedule!F:F,MATCH(24,Schedule!A:A,0))
A5: Check_interest_plus_principal_vs_payments_24m | B5: =SUM(Schedule!C2:C25)+SUM(Schedule!E2:E25) | C5: =SUM(Schedule!D2:D25) | D5: =B5-C5
