Workbook

Sheet Inputs
A1: 成本输入（千美元；黄色=输入）
A2: 折现率 | B2: 0.08
A4: 项目 | B4: Vendor A | C4: Vendor B | D4: Vendor C | E4: 时点
A5: 实施 (t0) | B5: 220 | C5: 150 | D5: 300 | E5: t=0
A6: 培训 (t0) | B6: 60 | C6: 90 | D6: 40 | E6: t=0
A7: Y1 许可 | B7: 380 | C7: 300 | D7: 450 | E7: Y1 末
A8: Y2 许可 | B8: 380 | C8: 315 | D8: 450 | E8: Y2 末
A9: Y3 许可 | B9: 380 | C9: 331 | D9: 450 | E9: Y3 末
A10: 每年支持 | B10: 40 | C10: 65 | D10: 25 | E10: 每年末
A11: 每年预期停机成本 | B11: 25 | C11: 80 | D11: 10 | E11: 每年末
A12: Y1 迁移费 | B12: 0 | C12: 50 | D12: 0 | E12: Y1 末
A13: Y3 残值/退出回收（抵减） | B13: 0 | C13: 0 | D13: 120 | E13: Y3 末，负成本

Sheet NPV
A1: 三年 TCO 现金流与 NPV（千美元；全部为公式；成本为正，残值为负）
A2: 年份 t | B2: 折现因子 1/(1+r)^t | C2: Vendor A 现金流 | D2: Vendor B 现金流 | E2: Vendor C 现金流 | F2: Vendor A PV | G2: Vendor B PV | H2: Vendor C PV
A3: 0 | B3: =1/(1+Inputs!$B$2)^A3 | C3: =Inputs!B5+Inputs!B6 | D3: =Inputs!C5+Inputs!C6 | E3: =Inputs!D5+Inputs!D6 | F3: =C3*$B3 | G3: =D3*$B3 | H3: =E3*$B3
A4: 1 | B4: =1/(1+Inputs!$B$2)^A4 | C4: =Inputs!B7+Inputs!B10+Inputs!B11+Inputs!B12 | D4: =Inputs!C7+Inputs!C10+Inputs!C11+Inputs!C12 | E4: =Inputs!D7+Inputs!D10+Inputs!D11+Inputs!D12 | F4: =C4*$B4 | G4: =D4*$B4 | H4: =E4*$B4
A5: 2 | B5: =1/(1+Inputs!$B$2)^A5 | C5: =Inputs!B8+Inputs!B10+Inputs!B11 | D5: =Inputs!C8+Inputs!C10+Inputs!C11 | E5: =Inputs!D8+Inputs!D10+Inputs!D11 | F5: =C5*$B5 | G5: =D5*$B5 | H5: =E5*$B5
A6: 3 | B6: =1/(1+Inputs!$B$2)^A6 | C6: =Inputs!B9+Inputs!B10+Inputs!B11-Inputs!B13 | D6: =Inputs!C9+Inputs!C10+Inputs!C11-Inputs!C13 | E6: =Inputs!D9+Inputs!D10+Inputs!D11-Inputs!D13 | F6: =C6*$B6 | G6: =D6*$B6 | H6: =E6*$B6
A8: 名义合计（未折现） | C8: =SUM(C3:C6) | D8: =SUM(D3:D6) | E8: =SUM(E3:E6)
A9: NPV（折现成本合计） | C9: =SUM(F3:F6) | D9: =SUM(G3:G6) | E9: =SUM(H3:H6)
A10: NPV 排名（1=最低） | C10: =RANK(C9,$C$9:$E$9,1) | D10: =RANK(D9,$C$9:$E$9,1) | E10: =RANK(E9,$C$9:$E$9,1)
A11: NPV 相对最低者差额 | C11: =C9-MIN($C$9:$E$9) | D11: =D9-MIN($C$9:$E$9) | E11: =E9-MIN($C$9:$E$9)
A12: NPV 校验 =NPV() 函数（t0 + NPV(t1..t3)） | C12: =C3+NPV(Inputs!$B$2,C4:C6) | D12: =D3+NPV(Inputs!$B$2,D4:D6) | E12: =E3+NPV(Inputs!$B$2,E4:E6)
A14: 汇总
A15: 供应商 | B15: NPV | C15: 名义合计 | D15: 排名
A16: Vendor A | B16: =C9 | C16: =C8 | D16: =C10
A17: Vendor B | B17: =D9 | C17: =D8 | D17: =D10
A18: Vendor C | B18: =E9 | C18: =E8 | D18: =E10

Sheet Sensitivity
A1: 敏感性分析（千美元；公式重算 NPV）
A2: 情景 1：Vendor B 年停机成本假设变化（其余不变）
A3: B 年停机成本 | B3: Vendor A NPV | C3: Vendor B NPV | D3: Vendor C NPV | E3: 最低 NPV 供应商
A4: 25 | B4: =(Inputs!B5+Inputs!B6)+(Inputs!B7+Inputs!B10+Inputs!B11+Inputs!B12)/(1+Inputs!$B$2)+(Inputs!B8+Inputs!B10+Inputs!B11)/(1+Inputs!$B$2)^2+(Inputs!B9+Inputs!B10+Inputs!B11-Inputs!B13)/(1+Inputs!$B$2)^3 | C4: =(Inputs!C5+Inputs!C6)+(Inputs!C7+Inputs!C10+$A4+Inputs!C12)/(1+Inputs!$B$2)+(Inputs!C8+Inputs!C10+$A4)/(1+Inputs!$B$2)^2+(Inputs!C9+Inputs!C10+$A4-Inputs!C13)/(1+Inputs!$B$2)^3 | D4: =(Inputs!D5+Inputs!D6)+(Inputs!D7+Inputs!D10+Inputs!D11+Inputs!D12)/(1+Inputs!$B$2)+(Inputs!D8+Inputs!D10+Inputs!D11)/(1+Inputs!$B$2)^2+(Inputs!D9+Inputs!D10+Inputs!D11-Inputs!D13)/(1+Inputs!$B$2)^3 | E4: =INDEX({"Vendor A","Vendor B","Vendor C"},MATCH(MIN(B4:D4),B4:D4,0))
A5: 40 | B5: =(Inputs!B5+Inputs!B6)+(Inputs!B7+Inputs!B10+Inputs!B11+Inputs!B12)/(1+Inputs!$B$2)+(Inputs!B8+Inputs!B10+Inputs!B11)/(1+Inputs!$B$2)^2+(Inputs!B9+Inputs!B10+Inputs!B11-Inputs!B13)/(1+Inputs!$B$2)^3 | C5: =(Inputs!C5+Inputs!C6)+(Inputs!C7+Inputs!C10+$A5+Inputs!C12)/(1+Inputs!$B$2)+(Inputs!C8+Inputs!C10+$A5)/(1+Inputs!$B$2)^2+(Inputs!C9+Inputs!C10+$A5-Inputs!C13)/(1+Inputs!$B$2)^3 | D5: =(Inputs!D5+Inputs!D6)+(Inputs!D7+Inputs!D10+Inputs!D11+Inputs!D12)/(1+Inputs!$B$2)+(Inputs!D8+Inputs!D10+Inputs!D11)/(1+Inputs!$B$2)^2+(Inputs!D9+Inputs!D10+Inputs!D11-Inputs!D13)/(1+Inputs!$B$2)^3 | E5: =INDEX({"Vendor A","Vendor B","Vendor C"},MATCH(MIN(B5:D5),B5:D5,0))
A6: 60 | B6: =(Inputs!B5+Inputs!B6)+(Inputs!B7+Inputs!B10+Inputs!B11+Inputs!B12)/(1+Inputs!$B$2)+(Inputs!B8+Inputs!B10+Inputs!B11)/(1+Inputs!$B$2)^2+(Inputs!B9+Inputs!B10+Inputs!B11-Inputs!B13)/(1+Inputs!$B$2)^3 | C6: =(Inputs!C5+Inputs!C6)+(Inputs!C7+Inputs!C10+$A6+Inputs!C12)/(1+Inputs!$B$2)+(Inputs!C8+Inputs!C10+$A6)/(1+Inputs!$B$2)^2+(Inputs!C9+Inputs!C10+$A6-Inputs!C13)/(1+Inputs!$B$2)^3 | D6: =(Inputs!D5+Inputs!D6)+(Inputs!D7+Inputs!D10+Inputs!D11+Inputs!D12)/(1+Inputs!$B$2)+(Inputs!D8+Inputs!D10+Inputs!D11)/(1+Inputs!$B$2)^2+(Inputs!D9+Inputs!D10+Inputs!D11-Inputs!D13)/(1+Inputs!$B$2)^3 | E6: =INDEX({"Vendor A","Vendor B","Vendor C"},MATCH(MIN(B6:D6),B6:D6,0))
A7: 80 | B7: =(Inputs!B5+Inputs!B6)+(Inputs!B7+Inputs!B10+Inputs!B11+Inputs!B12)/(1+Inputs!$B$2)+(Inputs!B8+Inputs!B10+Inputs!B11)/(1+Inputs!$B$2)^2+(Inputs!B9+Inputs!B10+Inputs!B11-Inputs!B13)/(1+Inputs!$B$2)^3 | C7: =(Inputs!C5+Inputs!C6)+(Inputs!C7+Inputs!C10+$A7+Inputs!C12)/(1+Inputs!$B$2)+(Inputs!C8+Inputs!C10+$A7)/(1+Inputs!$B$2)^2+(Inputs!C9+Inputs!C10+$A7-Inputs!C13)/(1+Inputs!$B$2)^3 | D7: =(Inputs!D5+Inputs!D6)+(Inputs!D7+Inputs!D10+Inputs!D11+Inputs!D12)/(1+Inputs!$B$2)+(Inputs!D8+Inputs!D10+Inputs!D11)/(1+Inputs!$B$2)^2+(Inputs!D9+Inputs!D10+Inputs!D11-Inputs!D13)/(1+Inputs!$B$2)^3 | E7: =INDEX({"Vendor A","Vendor B","Vendor C"},MATCH(MIN(B7:D7),B7:D7,0))
A8: 100 | B8: =(Inputs!B5+Inputs!B6)+(Inputs!B7+Inputs!B10+Inputs!B11+Inputs!B12)/(1+Inputs!$B$2)+(Inputs!B8+Inputs!B10+Inputs!B11)/(1+Inputs!$B$2)^2+(Inputs!B9+Inputs!B10+Inputs!B11-Inputs!B13)/(1+Inputs!$B$2)^3 | C8: =(Inputs!C5+Inputs!C6)+(Inputs!C7+Inputs!C10+$A8+Inputs!C12)/(1+Inputs!$B$2)+(Inputs!C8+Inputs!C10+$A8)/(1+Inputs!$B$2)^2+(Inputs!C9+Inputs!C10+$A8-Inputs!C13)/(1+Inputs!$B$2)^3 | D8: =(Inputs!D5+Inputs!D6)+(Inputs!D7+Inputs!D10+Inputs!D11+Inputs!D12)/(1+Inputs!$B$2)+(Inputs!D8+Inputs!D10+Inputs!D11)/(1+Inputs!$B$2)^2+(Inputs!D9+Inputs!D10+Inputs!D11-Inputs!D13)/(1+Inputs!$B$2)^3 | E8: =INDEX({"Vendor A","Vendor B","Vendor C"},MATCH(MIN(B8:D8),B8:D8,0))
A10: 情景 2：Vendor A 年停机成本翻倍风险（A 客户参考少）
A11: A 年停机成本 | B11: Vendor A NPV | C11: Vendor B NPV | D11: Vendor C NPV | E11: 最低 NPV 供应商
A12: 25 | B12: =(Inputs!B5+Inputs!B6)+(Inputs!B7+Inputs!B10+$A12+Inputs!B12)/(1+Inputs!$B$2)+(Inputs!B8+Inputs!B10+$A12)/(1+Inputs!$B$2)^2+(Inputs!B9+Inputs!B10+$A12-Inputs!B13)/(1+Inputs!$B$2)^3 | C12: =(Inputs!C5+Inputs!C6)+(Inputs!C7+Inputs!C10+Inputs!C11+Inputs!C12)/(1+Inputs!$B$2)+(Inputs!C8+Inputs!C10+Inputs!C11)/(1+Inputs!$B$2)^2+(Inputs!C9+Inputs!C10+Inputs!C11-Inputs!C13)/(1+Inputs!$B$2)^3 | D12: =(Inputs!D5+Inputs!D6)+(Inputs!D7+Inputs!D10+Inputs!D11+Inputs!D12)/(1+Inputs!$B$2)+(Inputs!D8+Inputs!D10+Inputs!D11)/(1+Inputs!$B$2)^2+(Inputs!D9+Inputs!D10+Inputs!D11-Inputs!D13)/(1+Inputs!$B$2)^3 | E12: =INDEX({"Vendor A","Vendor B","Vendor C"},MATCH(MIN(B12:D12),B12:D12,0))
A13: 50 | B13: =(Inputs!B5+Inputs!B6)+(Inputs!B7+Inputs!B10+$A13+Inputs!B12)/(1+Inputs!$B$2)+(Inputs!B8+Inputs!B10+$A13)/(1+Inputs!$B$2)^2+(Inputs!B9+Inputs!B10+$A13-Inputs!B13)/(1+Inputs!$B$2)^3 | C13: =(Inputs!C5+Inputs!C6)+(Inputs!C7+Inputs!C10+Inputs!C11+Inputs!C12)/(1+Inputs!$B$2)+(Inputs!C8+Inputs!C10+Inputs!C11)/(1+Inputs!$B$2)^2+(Inputs!C9+Inputs!C10+Inputs!C11-Inputs!C13)/(1+Inputs!$B$2)^3 | D13: =(Inputs!D5+Inputs!D6)+(Inputs!D7+Inputs!D10+Inputs!D11+Inputs!D12)/(1+Inputs!$B$2)+(Inputs!D8+Inputs!D10+Inputs!D11)/(1+Inputs!$B$2)^2+(Inputs!D9+Inputs!D10+Inputs!D11-Inputs!D13)/(1+Inputs!$B$2)^3 | E13: =INDEX({"Vendor A","Vendor B","Vendor C"},MATCH(MIN(B13:D13),B13:D13,0))
A14: 75 | B14: =(Inputs!B5+Inputs!B6)+(Inputs!B7+Inputs!B10+$A14+Inputs!B12)/(1+Inputs!$B$2)+(Inputs!B8+Inputs!B10+$A14)/(1+Inputs!$B$2)^2+(Inputs!B9+Inputs!B10+$A14-Inputs!B13)/(1+Inputs!$B$2)^3 | C14: =(Inputs!C5+Inputs!C6)+(Inputs!C7+Inputs!C10+Inputs!C11+Inputs!C12)/(1+Inputs!$B$2)+(Inputs!C8+Inputs!C10+Inputs!C11)/(1+Inputs!$B$2)^2+(Inputs!C9+Inputs!C10+Inputs!C11-Inputs!C13)/(1+Inputs!$B$2)^3 | D14: =(Inputs!D5+Inputs!D6)+(Inputs!D7+Inputs!D10+Inputs!D11+Inputs!D12)/(1+Inputs!$B$2)+(Inputs!D8+Inputs!D10+Inputs!D11)/(1+Inputs!$B$2)^2+(Inputs!D9+Inputs!D10+Inputs!D11-Inputs!D13)/(1+Inputs!$B$2)^3 | E14: =INDEX({"Vendor A","Vendor B","Vendor C"},MATCH(MIN(B14:D14),B14:D14,0))
A16: 情景 3：折现率
A17: 折现率 | B17: Vendor A NPV | C17: Vendor B NPV | D17: Vendor C NPV | E17: 最低 NPV 供应商
A18: 0.06 | B18: =(Inputs!B5+Inputs!B6)+(Inputs!B7+Inputs!B10+Inputs!B11+Inputs!B12)/(1+$A18)+(Inputs!B8+Inputs!B10+Inputs!B11)/(1+$A18)^2+(Inputs!B9+Inputs!B10+Inputs!B11-Inputs!B13)/(1+$A18)^3 | C18: =(Inputs!C5+Inputs!C6)+(Inputs!C7+Inputs!C10+Inputs!C11+Inputs!C12)/(1+$A18)+(Inputs!C8+Inputs!C10+Inputs!C11)/(1+$A18)^2+(Inputs!C9+Inputs!C10+Inputs!C11-Inputs!C13)/(1+$A18)^3 | D18: =(Inputs!D5+Inputs!D6)+(Inputs!D7+Inputs!D10+Inputs!D11+Inputs!D12)/(1+$A18)+(Inputs!D8+Inputs!D10+Inputs!D11)/(1+$A18)^2+(Inputs!D9+Inputs!D10+Inputs!D11-Inputs!D13)/(1+$A18)^3 | E18: =INDEX({"Vendor A","Vendor B","Vendor C"},MATCH(MIN(B18:D18),B18:D18,0))
A19: 0.08 | B19: =(Inputs!B5+Inputs!B6)+(Inputs!B7+Inputs!B10+Inputs!B11+Inputs!B12)/(1+$A19)+(Inputs!B8+Inputs!B10+Inputs!B11)/(1+$A19)^2+(Inputs!B9+Inputs!B10+Inputs!B11-Inputs!B13)/(1+$A19)^3 | C19: =(Inputs!C5+Inputs!C6)+(Inputs!C7+Inputs!C10+Inputs!C11+Inputs!C12)/(1+$A19)+(Inputs!C8+Inputs!C10+Inputs!C11)/(1+$A19)^2+(Inputs!C9+Inputs!C10+Inputs!C11-Inputs!C13)/(1+$A19)^3 | D19: =(Inputs!D5+Inputs!D6)+(Inputs!D7+Inputs!D10+Inputs!D11+Inputs!D12)/(1+$A19)+(Inputs!D8+Inputs!D10+Inputs!D11)/(1+$A19)^2+(Inputs!D9+Inputs!D10+Inputs!D11-Inputs!D13)/(1+$A19)^3 | E19: =INDEX({"Vendor A","Vendor B","Vendor C"},MATCH(MIN(B19:D19),B19:D19,0))
A20: 0.1 | B20: =(Inputs!B5+Inputs!B6)+(Inputs!B7+Inputs!B10+Inputs!B11+Inputs!B12)/(1+$A20)+(Inputs!B8+Inputs!B10+Inputs!B11)/(1+$A20)^2+(Inputs!B9+Inputs!B10+Inputs!B11-Inputs!B13)/(1+$A20)^3 | C20: =(Inputs!C5+Inputs!C6)+(Inputs!C7+Inputs!C10+Inputs!C11+Inputs!C12)/(1+$A20)+(Inputs!C8+Inputs!C10+Inputs!C11)/(1+$A20)^2+(Inputs!C9+Inputs!C10+Inputs!C11-Inputs!C13)/(1+$A20)^3 | D20: =(Inputs!D5+Inputs!D6)+(Inputs!D7+Inputs!D10+Inputs!D11+Inputs!D12)/(1+$A20)+(Inputs!D8+Inputs!D10+Inputs!D11)/(1+$A20)^2+(Inputs!D9+Inputs!D10+Inputs!D11-Inputs!D13)/(1+$A20)^3 | E20: =INDEX({"Vendor A","Vendor B","Vendor C"},MATCH(MIN(B20:D20),B20:D20,0))
A21: 0.12 | B21: =(Inputs!B5+Inputs!B6)+(Inputs!B7+Inputs!B10+Inputs!B11+Inputs!B12)/(1+$A21)+(Inputs!B8+Inputs!B10+Inputs!B11)/(1+$A21)^2+(Inputs!B9+Inputs!B10+Inputs!B11-Inputs!B13)/(1+$A21)^3 | C21: =(Inputs!C5+Inputs!C6)+(Inputs!C7+Inputs!C10+Inputs!C11+Inputs!C12)/(1+$A21)+(Inputs!C8+Inputs!C10+Inputs!C11)/(1+$A21)^2+(Inputs!C9+Inputs!C10+Inputs!C11-Inputs!C13)/(1+$A21)^3 | D21: =(Inputs!D5+Inputs!D6)+(Inputs!D7+Inputs!D10+Inputs!D11+Inputs!D12)/(1+$A21)+(Inputs!D8+Inputs!D10+Inputs!D11)/(1+$A21)^2+(Inputs!D9+Inputs!D10+Inputs!D11-Inputs!D13)/(1+$A21)^3 | E21: =INDEX({"Vendor A","Vendor B","Vendor C"},MATCH(MIN(B21:D21),B21:D21,0))
A23: Vendor B 停机成本盈亏平衡点（使 B 的 NPV 等于 A 的 NPV，按年停机成本）
A24: 年金因子 Σ1/(1+r)^t, t=1..3 | B24: =1/(1+Inputs!B2)+1/(1+Inputs!B2)^2+1/(1+Inputs!B2)^3
A25: B 停机成本为 0 时的 NPV | B25: =(Inputs!C5+Inputs!C6)+(Inputs!C7+Inputs!C10+0+Inputs!C12)/(1+Inputs!$B$2)+(Inputs!C8+Inputs!C10+0)/(1+Inputs!$B$2)^2+(Inputs!C9+Inputs!C10+0-Inputs!C13)/(1+Inputs!$B$2)^3
A26: 使 B = A 的年停机成本 | B26: =(NPV!C9-B25)/B24

Sheet Recommendation
A1: 采购建议
A2: 采购建议（≤500 字）：按 8% 折现，三年 TCO 的 NPV 为 Vendor A 1,426.8、Vendor B 1,470.6、Vendor C 1,494.6 千美元（测算），A 最低，比 B 低 43.7、比 C 低 67.8。名义合计 A 1,615、B 1,671、C 1,675。建议：以 Vendor A 为首选，但附三项条件：① 在签约前完成对其仅有的两个同规模客户的深度参考访谈与一次架构评审，若无法完成则转向 Vendor C；② 合同写入可用性 SLA 与停机服务抵扣，因为 A 的优势建立在年停机成本 25 的假设上——若 A 的停机成本升至 50，其 NPV 升至约 1,491，与 C 几乎持平（敏感性表情景 2）；③ 锁定三年许可价格。不选 Vendor B 的原因：名义许可费最低，但许可价逐年上涨、迁移费 50、年支持 65 与停机成本 80 使其 NPV 反而高于 A；且停机成本假设最不确定——只有当 B 的年停机成本降至约 63 以下（敏感性 B26 盈亏平衡点，测算）才会低于 A，而 B 的当前假设为 80。Vendor C 的非价格优势明显：六个同规模客户、最低停机成本 10、Y3 残值 120，是风险最低的选项；若运营对 A 的客户基础顾虑无法通过参考访谈消除，C 是可接受的次选，代价是 NPV 高出约 67.8。折现率在 6%–12% 区间内不改变 A 最低的排序（敏感性情景 3）。
A4: 字数 | B4: 425
A5: NPV A / B / C（引用） | B5: =NPV!C9 | C5: =NPV!D9 | D5: =NPV!E9
