Workbook

Sheet Detail
A1: Q1 月度预算与实际（千美元）；差异 = Actual − Budget；正数 = Unfavorable（费用超支）
A2: Department | B2: Jan Budget | C2: Jan Actual | D2: Jan Var | E2: Feb Budget | F2: Feb Actual | G2: Feb Var | H2: Mar Budget | I2: Mar Actual | J2: Mar Var | K2: Q1 Budget | L2: Q1 Actual | M2: Q1 Var | N2: Q1 Var % | O2: Status | P2: Flag
A3: Marketing | B3: 100 | C3: 105 | D3: =C3-B3 | E3: 110 | F3: 98 | G3: =F3-E3 | H3: 120 | I3: 150 | J3: =I3-H3 | K3: =B3+E3+H3 | L3: =C3+F3+I3 | M3: =L3-K3 | N3: =IF(K3=0,0,M3/K3) | O3: =IF(M3>0,"Unfavorable",IF(M3<0,"Favorable","On budget")) | P3: =IF(AND(M3>0,OR(M3>20,N3>0.05)),"RED",IF(M3<0,"GREEN","WATCH"))
A4: R&D | B4: 200 | C4: 190 | D4: =C4-B4 | E4: 210 | F4: 230 | G4: =F4-E4 | H4: 220 | I4: 250 | J4: =I4-H4 | K4: =B4+E4+H4 | L4: =C4+F4+I4 | M4: =L4-K4 | N4: =IF(K4=0,0,M4/K4) | O4: =IF(M4>0,"Unfavorable",IF(M4<0,"Favorable","On budget")) | P4: =IF(AND(M4>0,OR(M4>20,N4>0.05)),"RED",IF(M4<0,"GREEN","WATCH"))
A5: G&A | B5: 80 | C5: 78 | D5: =C5-B5 | E5: 80 | F5: 82 | G5: =F5-E5 | H5: 85 | I5: 80 | J5: =I5-H5 | K5: =B5+E5+H5 | L5: =C5+F5+I5 | M5: =L5-K5 | N5: =IF(K5=0,0,M5/K5) | O5: =IF(M5>0,"Unfavorable",IF(M5<0,"Favorable","On budget")) | P5: =IF(AND(M5>0,OR(M5>20,N5>0.05)),"RED",IF(M5<0,"GREEN","WATCH"))
A6: Sales | B6: 150 | C6: 145 | D6: =C6-B6 | E6: 160 | F6: 175 | G6: =F6-E6 | H6: 170 | I6: 185 | J6: =I6-H6 | K6: =B6+E6+H6 | L6: =C6+F6+I6 | M6: =L6-K6 | N6: =IF(K6=0,0,M6/K6) | O6: =IF(M6>0,"Unfavorable",IF(M6<0,"Favorable","On budget")) | P6: =IF(AND(M6>0,OR(M6>20,N6>0.05)),"RED",IF(M6<0,"GREEN","WATCH"))
A7: Total | B7: =SUM(B3:B6) | C7: =SUM(C3:C6) | D7: =SUM(D3:D6) | E7: =SUM(E3:E6) | F7: =SUM(F3:F6) | G7: =SUM(G3:G6) | H7: =SUM(H3:H6) | I7: =SUM(I3:I6) | ... M7: =SUM(M3:M6) | N7: =IF(K7=0,0,M7/K7) | O7: =IF(M7>0,"Unfavorable",IF(M7<0,"Favorable","On budget"))
A9: 阈值（管理层）：季度不利差异 > 20 千美元 或 差异率 > 5% → RED；有利差异 → GREEN；差异率 = Q1 Var / Q1 Budget（总预算作分母）。黄色=输入，绿色=公式。
A10: 阈值-金额 | B10: 20
A11: 阈值-差异率 | B11: 0.05

Sheet Dept Summary
A1: 部门季度汇总（引用 Detail）
A2: Department | B2: Q1 Budget | C2: Q1 Actual | D2: Variance (A−B) | E2: Variance % | F2: Fav/Unfav | G2: Flag | H2: Jan Cum Var | I2: Feb Cum Var | J2: Mar Cum Var (=Q1)
A3: =Detail!A3 | B3: =Detail!K3 | C3: =Detail!L3 | D3: =Detail!M3 | E3: =Detail!N3 | F3: =Detail!O3 | G3: =Detail!P3 | H3: =Detail!D3 | I3: =Detail!D3+Detail!G3 | J3: =Detail!D3+Detail!G3+Detail!J3
A4: =Detail!A4 | B4: =Detail!K4 | C4: =Detail!L4 | D4: =Detail!M4 | E4: =Detail!N4 | F4: =Detail!O4 | G4: =Detail!P4 | H4: =Detail!D4 | I4: =Detail!D4+Detail!G4 | J4: =Detail!D4+Detail!G4+Detail!J4
A5: =Detail!A5 | B5: =Detail!K5 | C5: =Detail!L5 | D5: =Detail!M5 | E5: =Detail!N5 | F5: =Detail!O5 | G5: =Detail!P5 | H5: =Detail!D5 | I5: =Detail!D5+Detail!G5 | J5: =Detail!D5+Detail!G5+Detail!J5
A6: =Detail!A6 | B6: =Detail!K6 | C6: =Detail!L6 | D6: =Detail!M6 | E6: =Detail!N6 | F6: =Detail!O6 | G6: =Detail!P6 | H6: =Detail!D6 | I6: =Detail!D6+Detail!G6 | J6: =Detail!D6+Detail!G6+Detail!J6
A7: Total | B7: =SUM(B3:B6) | C7: =SUM(C3:C6) | D7: =SUM(D3:D6) | E7: =IF(B7=0,0,D7/B7) | H7: =SUM(H3:H6) | I7: =SUM(I3:I6) | J7: =SUM(J3:J6)
A8: Check: Total Var − Detail!M7 | D8: =D7-Detail!M7

Sheet Charts
A1: 管理图表（数据源：Dept Summary / Detail，均为公式）
A2: Department | B2: Q1 Variance | C2: Jan Cum | D2: Feb Cum | E2: Mar Cum
A3: ='Dept Summary'!A3 | B3: ='Dept Summary'!D3 | C3: ='Dept Summary'!H3 | D3: ='Dept Summary'!I3 | E3: ='Dept Summary'!J3
A4: ='Dept Summary'!A4 | B4: ='Dept Summary'!D4 | C4: ='Dept Summary'!H4 | D4: ='Dept Summary'!I4 | E4: ='Dept Summary'!J4
A5: ='Dept Summary'!A5 | B5: ='Dept Summary'!D5 | C5: ='Dept Summary'!H5 | D5: ='Dept Summary'!I5 | E5: ='Dept Summary'!J5
A6: ='Dept Summary'!A6 | B6: ='Dept Summary'!D6 | C6: ='Dept Summary'!H6 | D6: ='Dept Summary'!I6 | E6: ='Dept Summary'!J6
A9: Month | B9: Marketing | C9: R&D | D9: G&A | E9: Sales
A10: Jan | B10: =C3 | C10: =C4 | D10: =C5 | E10: =C6
A11: Feb | B11: =D3 | C11: =D4 | D11: =D5 | E11: =D6
A12: Mar | B12: =E3 | C12: =E4 | D12: =E5 | E12: =E6

Sheet Conclusions
A1: 三条管理结论（基于 Detail/Dept Summary 的公式结果）
A3: 1. Q1 总费用 1,768 千美元，超预算 83 千美元（+4.9%）；三个部门（Marketing、R&D、Sales）同时触发 RED 标记，仅 G&A 有利（−5，−2.0%）。
A4: 2. R&D 是最大不利差异来源：+40 千美元（+6.3%），且逐月恶化（−10 → +20 → +30），累计差异从 1 月的有利转为 3 月的显著不利，需要在 4 月前确认是计划外项目还是提前投入。
A5: 3. Marketing 3 月单月超支 30 千美元（+25%），使季度差异达 +23（+7.0%）成为差异率最高的部门；Sales +25（+5.2%）刚越过 5% 阈值，2–3 月连续超支 15，应核对是否与收入增长挂钩（题内无收入数据，待确认）。
A7: 公式引用核对：
A8: 总差异 ='Dept Summary'!D7 → | B8: ='Dept Summary'!D7
A9: 总差异率 ='Dept Summary'!E7 → | B9: ='Dept Summary'!E7
A10: RED 部门数 → | B10: =COUNTIF('Dept Summary'!G3:G6,"RED")
